Workbook

Sheet How to use
A1: GRAPES manual update worklist
A2: Built October 12, 2026 from the GRAPES Search+ site data (407 listings).
A4: How to use
A5: 1. Work down the Worklist tab in order. It is sorted by priority, then by the soonest estimated deadline.
A6: 2. Open the official link, find the current details, and update the record in the GRAPES backend.
A7: 3. Fill in the yellow columns (New deadline through Date checked). Leave a cell blank if nothing changed.
A8: 4. Pick a Status from the dropdown. The Summary tab tracks progress automatically.
A9: 5. Always paste the page you used in Source link. These answers will be the test set for the AI agent pilot.
A11: Columns
A12: Grey/blue columns come from the site data. Do not edit them.
A13: Yellow columns are yours to fill in.
A14: "Estimated next deadline" rolls the last known deadline forward a year. It is a guess to help prioritize, not a confirmed date.
... A29: Example of a completed row (yellow columns)
A30: New deadline | B30: New amount | C30: Source link | D30: Status | E30: Notes | F30: Checked by | G30: Date checked
A31: 46327 | B31: $30,000 stipend | C31: https://www.lbi.org/about/fellowships/lbi-daad-fellowships/ | D31: Updated | E31: Second deadline May 1 for spring cycle | F31: DW | G31: 46308

Sheet Worklist
A1: Priority | B1: Record # | C1: Title | D1: Sponsor | E1: Site status | F1: Season | G1: Deadline on file | H1: Estimated next deadline | I1: Days left | J1: Amount on file | K1: Official link | L1: New deadline | M1: New amount | N1: Source link | O1: Status | P1: Notes | Q1: Checked by | R1: Date checked
A2: 1 - Check now | B2: 712 | C2: Penn Postdoctoral Fellowships for Academic Diversity (Provost's Postdoctoral Fellowship) | D2: University of Pennsylvania (UPenn) | E2: Unverified | F2: Fall | G2: 45943 | H2: 46308 | I2: =IF(H2="","",H2-TODAY()) -> 1 | J2: $68,300 stipend in year one (increasing $2,000/year), plus a $7,000/year research and travel allowance and up to $5,000 relocation allowance | K2: Open page
A3: 1 - Check now | B3: 99 | C3: Fellowship in History of Art and Visual Culture | D3: The Metropolitan Museum of Art | E3: Unverified | F3: Fall | G3: 45947 | H3: 46312 | I3: =IF(H3="","",H3-TODAY()) -> 5 | J3: $53,000 (junior fellows) or $63,000 (senior fellows), plus a $6,000 travel stipend | K3: Open page
A4: 1 - Check now | B4: 1119 | C4: Leonard A. Lauder Fellowships in Modern Art | D4: Leonard A. Lauder Research Center for Modern Art | E4: Verified | F4: Fall | G4: 45947 | H4: 46312 | I4: =IF(H4="","",H4-TODAY()) -> 5 | J4: $6,000 travel stipend; additional stipend varies by fellowship type | K4: Open page
A5: 1 - Check now | B5: 545 | C5: Institute of European Studies (IES) & Center for German and European Studies CGES (General) Predissertation & Dissertation Fellowships | D5: University of California (UC), Berkeley | E5: Verified | F5: Winter | G5: 45962 | H5: 46327 | I5: =IF(H5="","",H5-TODAY()) -> 20 | J5: $3,000-$5,000 | K5: Open page
A6: 1 - Check now | B6: 309 | C6: Society of Exploration Geophysicists (SEG) Foundation Scholarships | D6: Society of Exploration Geophysicists (SEG) | E6: Verified | F6: Winter | G6: 45962 | H6: 46327 | I6: =IF(H6="","",H6-TODAY()) -> 20 | J6: $500 - $10,000 per year | K6: Open page
A7: 1 - Check now | B7: 34 | C7: Career Development Program (CDP) | D7: Leukemia and Lymphoma Society (LLS) | E7: Verified | F7: Fall | G7: 45976 | H7: 46341 | I7: =IF(H7="","",H7-TODAY()) -> 34 | J7: $65,000-$75,000/year | K7: Open page
A8: 1 - Check now | B8: 1107 | C8: NISO Plus Scholarship Award | D8: NISO | E8: Unverified | F8: Fall | G8: 45985 | H8: 46350 | I8: =IF(H8="","",H8-TODAY()) -> 43 | K8: Open page
A9: 1 - Check now | B9: 1120 | C9: Lafayette Fellowship | D9: French Embassy in the United States | E9: Verified | F9: Fall | G9: 45991 | H9: 46356 | I9: =IF(H9="","",H9-TODAY()) -> 49 | J9: Full funding for one year of master's study | K9: Open page
A10: 1 - Check now | B10: 914 | C10: Center for Engaged Scholarship Dissertation Fellowships | D10: The Center for Engaged Scholarship | E10: Verified | F10: Fall | G10: 45992 | H10: 46357 | I10: =IF(H10="","",H10-TODAY()) -> 50 | J10: $25,000 over 9 months | K10: Open page
A11: 1 - Check now | B11: 198 | C11: Kate Neal Kinley Memorial Fellowship | D11: University of Illinois Urbana-Champaign, College of Fine and Applied Arts | E11: Unverified | F11: Winter | G11: 45992 | H11: 46357 | I11: =IF(H11="","",H11-TODAY()) -> 50 | J11: $20,000 (art/design, dance, music, or theatre award) | K11: Open page
A12: 1 - Check now | B12: 1069 | C12: Postdoctoral Fellow in Conservation Science | D12: Getty Conservation Institute | E12: Unverified | F12: Winter | G12: 45992 | H12: 46357 | I12: =IF(H12="","",H12-TODAY()) -> 50 | J12: Annual stipend, health insurance, study-trip allowance, and Getty scholar housing (specific dollar amount not stated) | K12: Open page
A13: 1 - Check now | B13: 668 | C13: Summer Student Fellowships | D13: Parkinson's Disease Foundation (PDF) | E13: Verified | F13: Fall | G13: 45995 | H13: 46360 | I13: =IF(H13="","",H13-TODAY()) -> 53 | J13: $4,000 (plus optional $1,000 travel) | K13: Open page
A14: 1 - Check now | B14: 188 | C14: S.V. Ciriacy-Wantrup Postdoctoral Fellowships in Natural Resource Economics and Political Economy | D14: University of California (UC), Berkeley | E14: Unverified | F14: Fall | G14: 46003 | H14: 46368 | I14: =IF(H14="","",H14-TODAY()) -> 61 | J14: $69,073–$77,030 annually | K14: Open page
A15: 1 - Check now | B15: 140 | C15: Energy Fellowship Program | D15: Link Foundation | E15: Verified | F15: Winter | G15: 46005 | H15: 46370 | I15: =IF(H15="","",H15-TODAY()) -> 63 | J15: $35,000/year for two years ($70,000 total) | K15: Open page
A16: 1 - Check now | B16: 726 | C16: Davis Fellows for Peace | D16: Middlebury College | E16: Verified | F16: Fall | G16: 46006 | H16: 46371 | I16: =IF(H16="","",H16-TODAY()) -> 64 | J16: Full tuition, housing, and food for summer | K16: Open page
A17: 1 - Check now | B17: 510 | C17: Short-Term Fellowships | D17: John Carter Brown Library | E17: Unverified | F17: Spring | G17: 46012 | H17: 46377 | I17: =IF(H17="","",H17-TODAY()) -> 70 | J17: Varies by fellowship type | K17: Open page
A18: 1 - Check now | B18: 304 | C18: Harvard Program on U.S.-Japan Relations Postdoctoral Fellowships | D18: Harvard University, Program on U.S.- Japan Relations | E18: Unverified | F18: Fall | G18: 46021 | H18: 46386 | I18: =IF(H18="","",H18-TODAY()) -> 79 | J18: Year-long stipend (commencing August or September 2026) | K18: Open page
A19: 1 - Check now | B19: 396 | C19: Goldstine Fellowship | D19: IBM Thomas J. Watson Research Center, Business Analytics and Mathematical Sciences Dept. | E19: Unverified | F19: Fall | G19: 46022 | H19: 46387 | I19: =IF(H19="","",H19-TODAY()) -> 80 | J19: Competitive postdoctoral salary and benefits | K19: Open page
A20: 1 - Check now | B20: 1112 | C20: Roe L. Johns Student Travel Grant | D20: Association for Education Finance & Policy (AEFP) | E20: Unverified | F20: Winter | G20: 46022 | H20: 46387 | I20: =IF(H20="","",H20-TODAY()) -> 80 | J20: $500 | K20: Open page
... A38: 2 - Next | B38: 721 | C38: Josephine de Karman Fellowship | D38: Josephine De Karman Fellowship Trust | E38: Verified | F38: Winter | G38: 46051 | H38: 46416 | I38: =IF(H38="","",H38-TODAY()) -> 109 | J38: $28,000 | K38: Open page
A39: 2 - Next | B39: 686 | C39: NASA Space Technology Graduate Research Opportunities (NSTGRO) | D39: National Aeronautics and Space Administration (NASA) | E39: Unverified | F39: Winter | G39: 46051 | H39: 46416 | I39: =IF(H39="","",H39-TODAY()) -> 109 | K39: Open page
A40: 2 - Next | B40: 895 | C40: Taiwan Studies Graduate Research Fellowship | D40: Taiwan Ministry of Education / Taipei Economic and Cultural Office in Los Angeles | E40: Unverified | F40: Winter | G40: 46052 | H40: 46417 | I40: =IF(H40="","",H40-TODAY()) -> 110 | K40: Open page
A41: 2 - Next | B41: 1110 | C41: Applied Machine Learning Summer Research Fellowship | D41: Los Alamos National Laboratory (LANL) | E41: Unverified | F41: Winter | G41: 46053 | H41: 46418 | I41: =IF(H41="","",H41-TODAY()) -> 111 | J41: Paid fellowship plus travel reimbursement | K41: Open page
A42: 2 - Next | B42: 708 | C42: American Nuclear Society Scholarships | D42: American Nuclear Society (ANS) | E42: Verified | F42: Winter | G42: 46054 | H42: 46419 | I42: =IF(H42="","",H42-TODAY()) -> 112 | J42: $1,000–$5,000 depending on scholarship | K42: Open page
A43: 2 - Next | B43: 1050 | C43: Clark Bibliographical Fellowship | D43: William Andrews Clark Memorial Library | E43: Verified | F43: Winter | G43: 46054 | H43: 46419 | I43: =IF(H43="","",H43-TODAY()) -> 112 | J43: $12,000 for 3 months | K43: Open page
A44: 2 - Next | B44: 794 | C44: Clark Dissertation Fellowships | D44: UCLA Center for 17th & 18th Century Studies | E44: Verified | F44: Winter | G44: 46054 | H44: 46419 | I44: =IF(H44="","",H44-TODAY()) -> 112 | J44: $36,000 | K44: Open page
A45: 2 - Next | B45: 1049 | C45: Clark Predoctoral Fellowship | D45: William Andrews Clark Memorial Library | E45: Verified | F45: Winter | G45: 46054 | H45: 46419 | I45: =IF(H45="","",H45-TODAY()) -> 112 | J45: $4,000/month for 1–3 months | K45: Open page
A46: 2 - Next | B46: 1051 | C46: Clark Short-Term Fellowships | D46: William Andrews Clark Memorial Library | E46: Verified | F46: Winter | G46: 46054 | H46: 46419 | I46: =IF(H46="","",H46-TODAY()) -> 112 | J46: $4,000/month for 1–3 months | K46: Open page
A47: 2 - Next | B47: 468 | C47: Alvin H Johnson 50 Dissertation Fellowships | D47: American Musicological Society (AMS) | E47: Verified | F47: Spring | G47: 46055 | H47: 46420 | I47: =IF(H47="","",H47-TODAY()) -> 113 | J47: $25,000 for one year | K47: Open page
A48: 2 - Next | B48: 1019 | C48: Charles F. Scott Fellowship | D48: UCLA Graduate Division | E48: Verified | F48: Winter | G48: 46066 | H48: 46431 | I48: =IF(H48="","",H48-TODAY()) -> 124 | J48: Up to $15,000 | K48: Open page
A49: 2 - Next | B49: 772 | C49: Dr. Ursula Mandel Scholarship | D49: UCLA Graduate Division | E49: Verified | F49: Winter | G49: 46066 | H49: 46431 | I49: =IF(H49="","",H49-TODAY()) -> 124 | J49: $15,000 in fees | K49: Open page
A50: 2 - Next | B50: 769 | C50: Gold Shield Alumnae of UCLA | D50: UCLA Division of Graduate Education | E50: Unverified | F50: Winter | G50: 46066 | H50: 46431 | I50: =IF(H50="","",H50-TODAY()) -> 124 | K50: Open page
A51: 2 - Next | B51: 763 | C51: Graduate Research Mentorship (GRM) Program | D51: UCLA Graduate Division | E51: Verified | F51: Winter | G51: 46066 | H51: 46431 | I51: =IF(H51="","",H51-TODAY()) -> 124 | J51: $30,000 | K51: Open page
A52: 2 - Next | B52: 762 | C52: Graduate Summer Research Mentorship (GSRM) Program | D52: UCLA Graduate Division | E52: Verified | F52: Winter | G52: 46066 | H52: 46431 | I52: =IF(H52="","",H52-TODAY()) -> 124 | J52: Summer support (varies) | K52: Open page
A53: 2 - Next | B53: 774 | C53: Paulson Scholarship Fund | D53: UCLA Graduate Division | E53: Verified | F53: Winter | G53: 46066 | H53: 46431 | I53: =IF(H53="","",H53-TODAY()) -> 124 | J53: Up to $6,000 | K53: Open page
A54: 2 - Next | B54: 782 | C54: UCLA Faculty Women's Club (FWC) Scholarship | D54: UCLA Division of Graduate Education | E54: Unverified | F54: Winter | G54: 46066 | H54: 46431 | I54: =IF(H54="","",H54-TODAY()) -> 124 | K54: Open page
A55: 2 - Next | B55: 778 | C55: Werner R. Scott Fund | D55: UCLA Graduate Division | E55: Verified | F55: Winter | G55: 46066 | H55: 46431 | I55: =IF(H55="","",H55-TODAY()) -> 124 | J55: $8,000 | K55: Open page
A56: 2 - Next | B56: 775 | C56: Will Rogers Memorial Fellowship | D56: UCLA Graduate Division | E56: Verified | F56: Winter | G56: 46066 | H56: 46431 | I56: =IF(H56="","",H56-TODAY()) -> 124 | J56: $10,000 | K56: Open page
A57: 2 - Next | B57: 920 | C57: Fellowships for Study in Quebec | D57: Society of French and Francophone Teachers of America (SPFFA) | E57: Verified | F57: Spring | G57: 46068 | H57: 46433 | I57: =IF(H57="","",H57-TODAY()) -> 126 | J57: $1,500 - $25,000 (or $4,000 for summer Quebec programs) | K57: Open page
A58: 2 - Next | B58: 62 | C58: HSF Scholar Program | D58: Hispanic Scholarship Fund (HSF) | E58: Unverified | F58: Winter | G58: 46068 | H58: 46433 | I58: =IF(H58="","",H58-TODAY()) -> 126 | J58: $500–$5,000 based on financial need | K58: Open page
A59: 2 - Next | B59: 412 | C59: Smithsonian Environmental Research Center (SERC) Internship Program | D59: Smithsonian Environmental Research Center (SERC) | E59: Verified | F59: Winter | G59: 46068 | H59: 46433 | I59: =IF(H59="","",H59-TODAY()) -> 126 | J59: $700/week | K59: Open page
A60: 2 - Next | B60: 274 | C60: Chancellor's Doctoral Incentive Program (CDIP) | D60: California State University (CSU) | E60: Unverified | F60: Winter | G60: 46069 | H60: 46434 | I60: =IF(H60="","",H60-TODAY()) -> 127 | J60: Up to $10,000/year for 3 years (max $30,000), forgivable at 20%/year of full-time CSU teaching employment | K60: Open page
A61: 2 - Next | B61: 249 | C61: Graduate Student Research Grants (with ExxonMobil-sponsored awards) | D61: Geological Society of America (GSA) | E61: Unverified | F61: Winter | G61: 46071 | H61: 46436 | I61: =IF(H61="","",H61-TODAY()) -> 129 | J61: $7,500 (ExxonMobil-sponsored awards); other GSA research grants vary | K61: Open page
A62: 2 - Next | B62: 1063 | C62: Alisa Bierria Graduate Fellowship | D62: UCLA Center for the Study of Women | E62: Verified | F62: Winter | G62: 46080 | H62: 46445 | I62: =IF(H62="","",H62-TODAY()) -> 138 | K62: Open page
A63: 2 - Next | B63: 790 | C63: Elizabeth Blackwell, M.D. Award | D63: UCLA Center for the Study of Women | E63: Verified | F63: Winter | G63: 46080 | H63: 46445 | I63: =IF(H63="","",H63-TODAY()) -> 138 | J63: Monetary award (amount set annually by CSW) | K63: Open page
A64: 2 - Next | B64: 810 | C64: Jean Stone Dissertation Research Fellowship | D64: UCLA Center for the Study of Women | E64: Unverified | F64: Winter | G64: 46080 | H64: 46445 | I64: =IF(H64="","",H64-TODAY()) -> 138 | J64: Competitive award; amount set annually | K64: Open page
A65: 2 - Next | B65: 1064 | C65: Mariame Kaba Graduate Fellowship | D65: UCLA Center for the Study of Women | E65: Verified | F65: Winter | G65: 46080 | H65: 46445 | I65: =IF(H65="","",H65-TODAY()) -> 138 | J65: $2,000 | K65: Open page
A66: 2 - Next | B66: 811 | C66: Paula Stone Legal Research Fellowship | D66: UCLA Center for the Study of Women | E66: Unverified | F66: Winter | G66: 46080 | H66: 46445 | I66: =IF(H66="","",H66-TODAY()) -> 138 | J66: $3,000 | K66: Open page
A67: 2 - Next | B67: 61 | C67: Scoville Peace Fellowship | D67: The Herbert Scoville Jr. Peace Fellowship | E67: Unverified | F67: Fall | G67: 46080 | H67: 46445 | I67: =IF(H67="","",H67-TODAY()) -> 138 | J67: Salary, health insurance, and travel covered | K67: Open page
A68: 2 - Next | B68: 796 | C68: The Constance Coiner Graduate Fellowships | D68: UCLA Center for the Study of Women | E68: Verified | F68: Winter | G68: 46080 | H68: 46445 | I68: =IF(H68="","",H68-TODAY()) -> 138 | K68: Open page
A69: 2 - Next | B69: 804 | C69: The Penny Kanner Dissertation Research Fellowship | D69: UCLA Center for the Study of Women | E69: Verified | F69: Winter | G69: 46080 | H69: 46445 | I69: =IF(H69="","",H69-TODAY()) -> 138 | K69: Open page
A70: 2 - Next | B70: 1102 | C70: John Ries Scholarship | D70: Expanded Shale, Clay, and Slate Institute (ESCSI) | E70: Unverified | F70: Winter | G70: 46081 | H70: 46446 | I70: =IF(H70="","",H70-TODAY()) -> 139 | J70: $5,000 | K70: Open page
A71: 2 - Next | B71: 199 | C71: Advanced Simulation & Training Fellowships | D71: Link Foundation | E71: Verified | F71: Winter | G71: 46082 | H71: 46447 | I71: =IF(H71="","",H71-TODAY()) -> 140 | J71: $35,000/year for up to 2 years | K71: Open page
A72: 2 - Next | B72: 918 | C72: Jean and Marie-Louise Dufrenoy Scholarship | D72: Society of French and Francophone Teachers of America (SPFFA) | E72: Verified | F72: Spring | G72: 46082 | H72: 46447 | I72: =IF(H72="","",H72-TODAY()) -> 140 | J72: $25,000 per academic year | K72: Open page
A73: 2 - Next | B73: 786 | C73: The George and Sakaye Aratani Fellowship | D73: UCLA Paul I. and Hisako Terasaki Center for Japanese Studies | E73: Unverified | F73: Spring | G73: 46082 | H73: 46447 | I73: =IF(H73="","",H73-TODAY()) -> 140 | J73: Up to $8,000 | K73: Open page
A74: 2 - Next | B74: 787 | C74: The George and Sakaye Aratani Field Experience Scholarship | D74: UCLA Paul I. and Hisako Terasaki Center for Japanese Studies | E74: Unverified | F74: Spring | G74: 46082 | H74: 46447 | I74: =IF(H74="","",H74-TODAY()) -> 140 | J74: $25,000 | K74: Open page
A75: 2 - Next | B75: 789 | C75: The Hans H. Baerwald Graduate Student Fellowship | D75: UCLA Paul I. and Hisako Terasaki Center for Japanese Studies | E75: Unverified | F75: Spring | G75: 46082 | H75: 46447 | I75: =IF(H75="","",H75-TODAY()) -> 140 | J75: $10,000 | K75: Open page
A76: 2 - Next | B76: 884 | C76: Summer Student Research Assistantships | D76: National Radio Astronomy Observatory (NRAO) | E76: Verified | F76: Winter | G76: 46083 | H76: 46448 | I76: =IF(H76="","",H76-TODAY()) -> 141 | J76: Competitive stipend | K76: Open page
A77: 2 - Next | B77: 263 | C77: The Bancroft Library Study Award | D77: Kenneth E. and Dorothy V. Hill Fellowship Fund | E77: Verified | F77: Winter | G77: 46083 | H77: 46448 | I77: =IF(H77="","",H77-TODAY()) -> 141 | K77: Open page
A78: 2 - Next | B78: 1041 | C78: Eudora Welty Research Fellowship | D78: Mississippi Department of Archives and History | E78: Verified | F78: Winter | G78: 46087 | H78: 46452 | I78: =IF(H78="","",H78-TODAY()) -> 145 | J78: $5,000 | K78: Open page
A79: 2 - Next | B79: 791 | C79: Summer Dissertation/Pre-Dissertation Fellowship | D79: UCLA Center for European and Russian Studies (CERS) | E79: Verified | F79: Winter | G79: 46089 | H79: 46454 | I79: =IF(H79="","",H79-TODAY()) -> 147 | J79: Up to $5,000 | K79: Open page
A80: 2 - Next | B80: 792 | C80: Summer Language Study Grants | D80: UCLA Center for European and Russian Studies (CERS) | E80: Verified | F80: Winter | G80: 46089 | H80: 46454 | I80: =IF(H80="","",H80-TODAY()) -> 147 | J80: Up to $4,000 | K80: Open page
A81: 2 - Next | B81: 269 | C81: International Research Scientist Development Award (IRSDA) | D81: National Institutes of Health (NIH) | E81: Verified | F81: Winter | G81: 46090 | H81: 46455 | I81: =IF(H81="","",H81-TODAY()) -> 148 | J81: Salary and research support for 3-5 years | K81: Open page
A82: 2 - Next | B82: 479 | C82: California Science and Technology Policy Fellowships | D82: California Council on Science and Technology (CCST) | E82: Verified | F82: Winter | G82: 46091 | H82: 46456 | I82: =IF(H82="","",H82-TODAY()) -> 149 | J82: Competitive stipend plus health care costs | K82: Open page
A83: 2 - Next | B83: 406 | C83: Newton International Fellowship | D83: The Royal Society | E83: Unverified | F83: Winter | G83: 46092 | H83: 46457 | I83: =IF(H83="","",H83-TODAY()) -> 150 | J83: Funding cap of £280,000 (Royal Society scheme) | K83: Open page
A84: 2 - Next | B84: 1122 | C84: W.E.B. Du Bois Scholar Program | D84: Roper Center for Public Opinion | E84: Verified | F84: Winter | G84: 46094 | H84: 46459 | I84: =IF(H84="","",H84-TODAY()) -> 152 | J84: $5,000 + AAPOR membership | K84: Open page
A85: 2 - Next | B85: 919 | C85: Jeanne Marandon Fellowship | D85: Society of French and Francophone Teachers of America (SPFFA) | E85: Verified | F85: Spring | G85: 46096 | H85: 46461 | I85: =IF(H85="","",H85-TODAY()) -> 154 | J85: $1,500-$25,000 | K85: Open page
A86: 2 - Next | B86: 565 | C86: Pre-Dissertation Research Fellowships in European Studies | D86: Columbia University, Council for European Studies | E86: Unverified | F86: Fall | G86: 46096 | H86: 46461 | I86: =IF(H86="","",H86-TODAY()) -> 154 | J86: $5,000 plus conference registration waiver | K86: Open page
A87: 2 - Next | B87: 340 | C87: Research Fellowship Program | D87: Portland Cement Association (PCA) Education Foundation | E87: Verified | F87: Winter | G87: 46096 | H87: 46461 | I87: =IF(H87="","",H87-TODAY()) -> 154 | J87: $35,000 total award | K87: Open page
A88: 2 - Next | B88: 904 | C88: Blaustein Center (BCSC) Postdoctoral Fellowships | D88: The Jacob Blaustein Center for Scientific Cooperation (BCSC) | E88: Verified | F88: Winter | G88: 46098 | H88: 46463 | I88: =IF(H88="","",H88-TODAY()) -> 156 | J88: $26,000 annually (standard) or ~$29,000 (Distinguished); 1-2 year terms | K88: Open page
A89: 2 - Next | B89: 702 | C89: Dannon Gut Microbiome, Yogurt and Probiotics Fellowship Program | D89: The Dannon Company | E89: Verified | F89: Winter | G89: 46102 | H89: 46467 | I89: =IF(H89="","",H89-TODAY()) -> 160 | J89: $25,000 each for two recipients | K89: Open page
... A92: 2 - Next | B92: 1126 | C92: Arnold Rubin Award | D92: Fowler Museum at UCLA | E92: Verified | F92: Spring | G92: 46107 | H92: 46472 | I92: =IF(H92="","",H92-TODAY()) -> 165 | J92: $3,000-$4,000 | K92: Open page
A93: 2 - Next | B93: 480 | C93: Horton (Hydrology) Research Grant | D93: American Geophysical Union (AGU) | E93: Verified | F93: Spring | G93: 46108 | H93: 46473 | I93: =IF(H93="","",H93-TODAY()) -> 166 | K93: Open page
A94: 2 - Next | B94: 218 | C94: Center of Military History (CMH) Dissertation Fellowships | D94: National Museum of the United States Army | E94: Verified | F94: Fall | G94: 46112 | H94: 46477 | I94: =IF(H94="","",H94-TODAY()) -> 170 | J94: $15,000–$80,000 depending on fellowship tier | K94: Open page
A95: 2 - Next | B95: 1111 | C95: Cobell Scholarship | D95: Indigenous Education, Inc. (IEI) | E95: Unverified | F95: Spring | G95: 46112 | H95: 46477 | I95: =IF(H95="","",H95-TODAY()) -> 170 | K95: Open page
A96: 2 - Next | B96: 750 | C96: Deep Time Peter Buck Fellowship Peter Buck Deep Time Postdoctoral Fellowship | D96: Smithsonian Institution (SI) | E96: Verified | F96: Spring | G96: 46112 | H96: 46477 | I96: =IF(H96="","",H96-TODAY()) -> 170 | J96: $62,000/year stipend + $5,000 research/travel + $5,000 health insurance + $1,000 relocation | K96: Open page
A97: 2 - Next | B97: 928 | C97: Islamic Scholarship Fund (ISF) | D97: Islamic Scholarship Fund | E97: Verified | F97: Winter | G97: 46112 | H97: 46477 | I97: =IF(H97="","",H97-TODAY()) -> 170 | J97: Varies by fellowship ($40,000 Congressional; $10,000+ Journalism) | K97: Open page
A98: 2 - Next | B98: 324 | C98: Scholarship Program | D98: National Federation of the Blind (NFB) | E98: Verified | F98: Winter | G98: 46112 | H98: 46477 | I98: =IF(H98="","",H98-TODAY()) -> 170 | J98: $10,000 | K98: Open page
A99: 2 - Next | B99: 488 | C99: Graduate Fellowship for Alternatives to the Use of Animals in Science | D99: International Foundation for Ethical Research (IFER) | E99: Verified | F99: Spring | G99: 46113 | H99: 46478 | I99: =IF(H99="","",H99-TODAY()) -> 171 | J99: $15,000/year + $1,000 travel | K99: Open page
A100: 2 - Next | B100: 12 | C100: Newkirk Fellowship | D100: High Altitude Observatory (HAO) | E100: Unverified | F100: Winter | G100: 46113 | H100: 46478 | I100: =IF(H100="","",H100-TODAY()) -> 171 | K100: Open page
A101: 2 - Next | B101: 433 | C101: Postdoctoral Fellowship Program for Foreign Researchers | D101: Japanese Society for the Promotion of Science (JSPS) | E101: Verified | F101: Spring | G101: 46114 | H101: 46479 | I101: =IF(H101="","",H101-TODAY()) -> 172 | J101: JPY 362,000 per month plus settling-in allowance of JPY 200,000 and travel insurance | K101: Open page
A102: 2 - Next | B102: 1022 | C102: The Harry C. Sigman Graduate Fellowship | D102: UCLA Y&S Nazarian Center for Israel Studies | E102: Verified | F102: Spring | G102: 46117 | H102: 46482 | I102: =IF(H102="","",H102-TODAY()) -> 175 | J102: $8,000 | K102: Open page
A103: 3 - Later | B103: 405 | C103: Lemelson Center Fellowship Program | D103: Lemelson Center for the Study of Invention & Innovation | E103: Unverified | F103: Spring | G103: 46125 | H103: 46490 | I103: =IF(H103="","",H103-TODAY()) -> 183 | K103: Open page
A104: 3 - Later | B104: 538 | C104: National Health Service Corps (NHSC) Scholarship Program | D104: National Health Service Corps (NHSC), Health Resources and Services Administration (HRSA) | E104: Unverified | F104: Spring | G104: 46128 | H104: 46493 | I104: =IF(H104="","",H104-TODAY()) -> 186 | J104: Full tuition/fees plus a monthly stipend | K104: Open page
A105: 3 - Later | B105: 1094 | C105: Lee Schipper Memorial Scholarship for Sustainable Transport and Energy Efficiency | D105: Volvo Research and Educational Foundations | E105: Verified | F105: Spring | G105: 46129 | H105: 46494 | I105: =IF(H105="","",H105-TODAY()) -> 187 | J105: Up to $12,500 | K105: Open page
A106: 3 - Later | B106: 890 | C106: Lynn and Maude White Fellowship | D106: UCLA Center for Medieval & Renaissance Studies | E106: Verified | F106: Spring | G106: 46129 | H106: 46494 | I106: =IF(H106="","",H106-TODAY()) -> 187 | J106: $30,000 | K106: Open page
A107: 3 - Later | B107: 439 | C107: National Endowment for the Humanities NEH Fellowships | D107: National Endowment for the Humanities (NEH) | E107: Verified | F107: Spring | G107: 46134 | H107: 46499 | I107: =IF(H107="","",H107-TODAY()) -> 192 | J107: Up to $60,000 ($5,000/month for 6–12 months) | K107: Open page
A108: 3 - Later | B108: 367 | C108: New Investigators Research Grant | D108: American Speech-Language-Hearing Foundation (ASHFoundation) | E108: Verified | F108: Spring | G108: 46134 | H108: 46499 | I108: =IF(H108="","",H108-TODAY()) -> 192 | J108: $10,000 per grant (up to 10 awards) | K108: Open page
A109: 3 - Later | B109: 262 | C109: White House Fellowship Program | D109: White House | E109: Verified | F109: Winter | G109: 46134 | H109: 46499 | I109: =IF(H109="","",H109-TODAY()) -> 192 | J109: GS-14 federal salary | K109: Open page
A110: 3 - Later | B110: 813 | C110: Hiroshi Wagatsuma Memorial Fellowship | D110: UCLA Asia Institute | E110: Verified | F110: Spring | G110: 46143 | H110: 46508 | I110: =IF(H110="","",H110-TODAY()) -> 201 | J110: Up to $7,000 | K110: Open page
A111: 3 - Later | B111: 891 | C111: Graduate Certificate in Early Modern Studies | D111: UCLA Center for 17th & 18th Century Studies | E111: Verified | F111: Spring | G111: 46148 | H111: 46513 | I111: =IF(H111="","",H111-TODAY()) -> 206 | K111: Open page
A112: 3 - Later | B112: 1099 | C112: Diana Jacobs Kalman/AFAR Scholarships for Research in the Biology of Aging | D112: American Federation for Aging Research (AFAR) | E112: Unverified | F112: Winter | G112: 46150 | H112: 46515 | I112: =IF(H112="","",H112-TODAY()) -> 208 | J112: $5,000 | K112: Open page
A113: 3 - Later | B113: 705 | C113: GMiS STEM Scholarship Program (formerly HENAAC Scholars Program) | D113: Great Minds in STEM (GMiS) | E113: Unverified | F113: Spring | G113: 46150 | H113: 46515 | I113: =IF(H113="","",H113-TODAY()) -> 208 | J113: $500-$10,000 | K113: Open page
A114: 3 - Later | B114: 441 | C114: New Century Scholars Doctoral Scholarship | D114: American Speech-Language-Hearing Foundation (ASHFoundation) | E114: Verified | F114: Spring | G114: 46155 | H114: 46520 | I114: =IF(H114="","",H114-TODAY()) -> 213 | J114: $10,000 per scholarship (up to 15 awards) | K114: Open page
A115: 3 - Later | B115: 1101 | C115: Pivot Fellowship | D115: Simons Foundation | E115: Verified | F115: Spring | G115: 46156 | H115: 46521 | I115: =IF(H115="","",H115-TODAY()) -> 214 | J115: Full salary support plus $10,000 allowance | K115: Open page
A116: 3 - Later | B116: 732 | C116: Graduate Research Program on Public-Sector Aviation Issues | D116: Federal Aviation Administration (FAA) | E116: Verified | F116: Spring | G116: 46157 | H116: 46522 | I116: =IF(H116="","",H116-TODAY()) -> 215 | J116: $12,000 per award (up to 10 awards) | K116: Open page
A117: 3 - Later | B117: 370 | C117: Mexican American Legal Defense and Educational Fund (MALDEF) Law School Scholarship Program | D117: Mexican American Legal Defense and Educational Fund (MALDEF) | E117: Verified | F117: Fall | G117: 46157 | H117: 46522 | I117: =IF(H117="","",H117-TODAY()) -> 215 | J117: $2,000–$10,000 | K117: Open page
A118: 3 - Later | B118: 349 | C118: NBI Law Student Fellowship Program | D118: National Bar Association (NBA) | E118: Verified | F118: Spring | G118: 46157 | H118: 46522 | I118: =IF(H118="","",H118-TODAY()) -> 215 | J118: $1,000 to $10,000 | K118: Open page
A119: 3 - Later | B119: 637 | C119: World Wide Studies Grant | D119: Victor Pinchuk Foundation | E119: Verified | F119: Spring | G119: 46157 | H119: 46522 | I119: =IF(H119="","",H119-TODAY()) -> 215 | J119: Up to USD $50,000 (covers 60% of total costs) | K119: Open page
...

Sheet Summary
A1: Progress
A3: Priority | B3: Listings | C3: Checked | D3: Remaining | E3: % done
A4: 1 - Check now | B4: =COUNTIF(Worklist!$A$2:$A$408,A4) -> 24 | C4: =COUNTIFS(Worklist!$A$2:$A$408,A4,Worklist!$O$2:$O$408,"<>") -> 0 | D4: =B4-C4 -> 24 | E4: =IF(B4=0,0,C4/B4) -> 0
A5: 2 - Next | B5: =COUNTIF(Worklist!$A$2:$A$408,A5) -> 77 | C5: =COUNTIFS(Worklist!$A$2:$A$408,A5,Worklist!$O$2:$O$408,"<>") -> 0 | D5: =B5-C5 -> 77 | E5: =IF(B5=0,0,C5/B5) -> 0
A6: 3 - Later | B6: =COUNTIF(Worklist!$A$2:$A$408,A6) -> 86 | C6: =COUNTIFS(Worklist!$A$2:$A$408,A6,Worklist!$O$2:$O$408,"<>") -> 0 | D6: =B6-C6 -> 86 | E6: =IF(B6=0,0,C6/B6) -> 0
A7: 4 - Find a date | B7: =COUNTIF(Worklist!$A$2:$A$408,A7) -> 65 | C7: =COUNTIFS(Worklist!$A$2:$A$408,A7,Worklist!$O$2:$O$408,"<>") -> 0 | D7: =B7-C7 -> 65 | E7: =IF(B7=0,0,C7/B7) -> 0
A8: 5 - Rolling | B8: =COUNTIF(Worklist!$A$2:$A$408,A8) -> 26 | C8: =COUNTIFS(Worklist!$A$2:$A$408,A8,Worklist!$O$2:$O$408,"<>") -> 0 | D8: =B8-C8 -> 26 | E8: =IF(B8=0,0,C8/B8) -> 0
A9: 6 - Current | B9: =COUNTIF(Worklist!$A$2:$A$408,A9) -> 129 | C9: =COUNTIFS(Worklist!$A$2:$A$408,A9,Worklist!$O$2:$O$408,"<>") -> 0 | D9: =B9-C9 -> 129 | E9: =IF(B9=0,0,C9/B9) -> 0
A10: Total | B10: =SUM(B4:B9) -> 407 | C10: =SUM(C4:C9) -> 0 | D10: =SUM(D4:D9) -> 407 | E10: =IF(B10=0,0,C10/B10) -> 0
A12: By status
A13: Status | B13: Count
A14: Updated | B14: =COUNTIF(Worklist!$O$2:$O$408,A14) -> 0
A15: No change needed | B15: =COUNTIF(Worklist!$O$2:$O$408,A15) -> 0
A16: Not posted yet | B16: =COUNTIF(Worklist!$O$2:$O$408,A16) -> 0
A17: Discontinued / paused | B17: =COUNTIF(Worklist!$O$2:$O$408,A17) -> 0
A18: Link broken - new link found | B18: =COUNTIF(Worklist!$O$2:$O$408,A18) -> 0
A19: Link broken - not found | B19: =COUNTIF(Worklist!$O$2:$O$408,A19) -> 0
